{
  "HomeTitle": "Todo - Projects",
  "Projects": "Projects",
  "NewProjectPlaceholder": "New project name...",
  "DeleteProjectConfirm": "Delete project",
  "DeleteProjectWarning": "All tickets and associated data will be permanently deleted.",
  "Pause": "Pause",
  "Resume": "Resume",
  "Paused": "Paused",
  "CreationSetupIntro": "Configure the workspace for this new project, then click Initialize to create it and install the agent templates.",
  "OpenBoard": "Open board",
  "WorkspaceMissing": "This folder does not exist.",
  "CreateFolder": "Create folder",
  "FolderCreated": "Folder created."
}
